cns/DataX.cp36-win32.pyd
cns/DataX.cp36-win_amd64.pyd
cns/DataX.cp39-win_amd64.pyd
cns/DateTimeX.cp36-win32.pyd
cns/DateTimeX.cp36-win_amd64.pyd
cns/DateTimeX.cp39-win_amd64.pyd
cns/ExcelX.cp36-win32.pyd
cns/ExcelX.cp36-win_amd64.pyd
cns/ExcelX.cp39-win_amd64.pyd
cns/OTPX.cp36-win_amd64.pyd
cns/OTPX.cp39-win_amd64.pyd
cns/SQLstrX.cp36-win_amd64.pyd
cns/SQLstrX.cp39-win_amd64.pyd
cns/TextX.cp36-win_amd64.pyd
cns/TextX.cp39-win_amd64.pyd
cns/__init__.py
cns/cmdX.cp36-win32.pyd
cns/cmdX.cp36-win_amd64.pyd
cns/cmdX.cp39-win_amd64.pyd
cnk-1.8.8.dist-info/LICENSE
cnk-1.8.8.dist-info/METADATA
cnk-1.8.8.dist-info/WHEEL
cnk-1.8.8.dist-info/top_level.txt
cnk-1.8.8.dist-info/RECORD
