Metadata-Version: 2.1
Name: cnk
Version: 1.8.8
Summary: cnk内测工具包
Home-page: https://cns.ink/example
Author: Rambo
Author-email: 6566666@qq.com
License: Copyright (C) 2023 CNS. All Rights Reserved. See LICENSE for license.
Platform: UNKNOWN
Classifier: Development Status :: 3 - Alpha
Classifier: Programming Language :: Python :: 3
Classifier: License :: OSI Approved :: MIT License
Classifier: Operating System :: Microsoft :: Windows
Requires-Python: >=3.6
Requires-Dist: python-dateutil
